README.txt
setup.py
pySPIRALTAP/__init__.py
pySPIRALTAP/conv2.py
pySPIRALTAP/denoise_bound.py
pySPIRALTAP/haarApprox.py
pySPIRALTAP/pySPIRALTAP.py
pySPIRALTAP/subsolutions.py
pySPIRALTAP.egg-info/PKG-INFO
pySPIRALTAP.egg-info/SOURCES.txt
pySPIRALTAP.egg-info/dependency_links.txt
pySPIRALTAP.egg-info/requires.txt
pySPIRALTAP.egg-info/top_level.txt