Metadata-Version: 1.1
Name: pySPIRALTAP
Version: 0.4.12
Summary: A compressed sensing library for Python
Home-page: https://gitlab.com/padouppadoup/pySPIRAL-TAP/
Author: Maxime Woringer, Zachary Harmany
Author-email: maxime.woringer@ens.fr
License: unknown
Keywords: compressed sensing
Platform: UNKNOWN
Classifier: Development Status :: 3 - Alpha
Classifier: Intended Audience :: Science/Research
Classifier: Programming Language :: Python :: 2
Classifier: Programming Language :: Python :: 2.7
Classifier: Programming Language :: Python :: 3
Classifier: Programming Language :: Python :: 3.3
Classifier: Programming Language :: Python :: 3.4
Classifier: Programming Language :: Python :: 3.5
